aya_ha_debugger/__init__.py
aya_ha_debugger/core.py
aya_ha_debugger-0.1.0.dist-info/METADATA
aya_ha_debugger-0.1.0.dist-info/WHEEL
aya_ha_debugger-0.1.0.dist-info/RECORD
