Metadata-Version: 2.4
Name: aya_ha_debugger
Version: 0.1.0
Summary: A fun Python debugger that prints 'aya ha' instead of using print().
Author-email: Your Name <you@example.com>
License: MIT
Classifier: License :: OSI Approved :: MIT License
Classifier: Programming Language :: Python :: 3
Requires-Python: >=3.8
